gfa_ml/__init__.py
gfa_ml/custom/README.md
gfa_ml/custom/cost_function.py
gfa_ml/data_model/README.md
gfa_ml/data_model/common.py
gfa_ml/data_model/data_type.py
gfa_ml/data_model/ml_model.py
gfa_ml/data_model/storage.py
gfa_ml/lib/README.md
gfa_ml/lib/common.py
gfa_ml/lib/constant.py
gfa_ml/lib/data_processing.py
gfa_ml/lib/default.py
gfa_ml/lib/hyper_parameter_tuning.py
gfa_ml/lib/optimization.py
gfa_ml/lib/optimization_v2.py
gfa_ml/lib/serving.py
gfa_ml/lib/storage.py
gfa_ml/lib/training.py
gfa_ml/lib/utils.py
gfa_ml-0.0.40.dist-info/METADATA
gfa_ml-0.0.40.dist-info/WHEEL
gfa_ml-0.0.40.dist-info/RECORD
