Metadata-Version: 2.4
Name: gfa_ml
Version: 0.0.40
Summary: ML library for end-to-end ML pipeline
Author: Minh-Tri Nguyen (GreenFactory.AI)
Author-email: tri@greenfactory.ai
Requires-Python: >=3.10, <3.14
Classifier: Programming Language :: Python :: 3
Classifier: Programming Language :: Python :: 3.10
Classifier: Programming Language :: Python :: 3.11
Classifier: Programming Language :: Python :: 3.12
Classifier: Programming Language :: Python :: 3.13
Provides-Extra: torch-cpu
Provides-Extra: training
Requires-Dist: ipykernel (>=6.30.1,<7.0.0) ; extra == "training"
Requires-Dist: matplotlib (>=3.10.5,<4.0.0) ; extra == "training"
Requires-Dist: mlflow (>=3.2.0,<4.0.0)
Requires-Dist: notebook (>=7.4.5,<8.0.0) ; extra == "training"
Requires-Dist: openpyxl (>=3.1.5,<4.0.0)
Requires-Dist: optuna (>=4.5.0,<5.0.0)
Requires-Dist: pandas (>=2.3.1,<3.0.0)
Requires-Dist: pydantic (>=2.11.7,<3.0.0)
Requires-Dist: pyyaml (>=6.0.2,<7.0.0)
Requires-Dist: scikit-learn (>=1.7.1,<2.0.0)
Requires-Dist: shap (>=0.48.0,<0.49.0) ; extra == "training"
Requires-Dist: torch (>=2.8.0,<3.0.0) ; extra == "torch-cpu"
Requires-Dist: torch (>=2.8.0,<3.0.0) ; extra == "training"
